[
 {
   "source": "CJTV MEDIA",
   "platform": "FACEBOOK",
   "link": "https://www.facebook.com/watch/?v=714881945807260"
 },
 {
   "source": "NEWS2SHARE",
   "platform": "FACEBOOK",
   "link": "https://www.facebook.com/watch/?v=1268759920190140"
 },
 {
   "source": "BURGERPLANET",
   "platform": "TWITCH",
   "link": "https://www.twitch.tv/burgerplanet"
 },
 {
   "source": "ROB CORTIS",
   "platform": "FACEBOOK",
   "link": "https://www.facebook.com/1590191578/videos/10221431941059864"
 },
 {
   "source": "SKY NEWS",
   "platform": "YOUTUBE",
   "link": "https://youtu.be/9Auq9mYxFEE"
 },
 {
   "source": "RIGHT SIDE BROADCAST NETWORK",
   "platform": "YOUTUBE",
   "link": "https://youtu.be/1mEgKX_mRtk"
 }
]
